mcp_feet_master/__init__.py
mcp_feet_master/__main__.py
mcp_feet_master/mineru_ocr.py
mcp_feet_master/monitor_vcp_code_setting.py
mcp_feet_master/server.py
mcp_feet_master-0.1.12.dist-info/licenses/LICENSE
mcp_feet_master-0.1.12.dist-info/METADATA
mcp_feet_master-0.1.12.dist-info/WHEEL
mcp_feet_master-0.1.12.dist-info/entry_points.txt
mcp_feet_master-0.1.12.dist-info/top_level.txt
mcp_feet_master-0.1.12.dist-info/RECORD
