Metadata-Version: 2.4
Name: mcp-feet-master
Version: 0.1.12
Summary: A Model Context Protocol server for calculating animal feet counts (rabbits and chickens)
Author-email: ThomasYang <tom19860526@gmail.com>
License: MIT
Project-URL: Homepage, https://github.com/yourusername/mcp-feet-master
Project-URL: Repository, https://github.com/yourusername/mcp-feet-master
Project-URL: Issues, https://github.com/yourusername/mcp-feet-master/issues
Keywords: mcp,model-context-protocol,feet,calculation,ai-tools
Classifier: Development Status :: 4 - Beta
Classifier: Intended Audience :: Developers
Classifier: License :: OSI Approved :: MIT License
Classifier: Programming Language :: Python :: 3
Classifier: Programming Language :: Python :: 3.8
Classifier: Programming Language :: Python :: 3.9
Classifier: Programming Language :: Python :: 3.10
Classifier: Programming Language :: Python :: 3.11
Classifier: Programming Language :: Python :: 3.12
Classifier: Topic :: Scientific/Engineering :: Mathematics
Classifier: Topic :: Software Development :: Libraries :: Python Modules
Requires-Python: >=3.8
License-File: LICENSE
Requires-Dist: mcp>=1.0.0
Requires-Dist: opencv-python>=4.8.0
Requires-Dist: numpy>=1.21.0
Provides-Extra: dev
Requires-Dist: black>=23.0; extra == "dev"
Requires-Dist: isort>=5.0; extra == "dev"
Provides-Extra: build
Requires-Dist: build>=0.10.0; extra == "build"
Requires-Dist: twine>=4.0.0; extra == "build"
Dynamic: license-file
